volume_plot_utils/__init__.py
volume_plot_utils/plotter.py
volume_plot_utils/template.html.txt
fMRI_Volumetric_Renderer-0.2.7.dist-info/LICENSE
fMRI_Volumetric_Renderer-0.2.7.dist-info/METADATA
fMRI_Volumetric_Renderer-0.2.7.dist-info/WHEEL
fMRI_Volumetric_Renderer-0.2.7.dist-info/top_level.txt
fMRI_Volumetric_Renderer-0.2.7.dist-info/RECORD
