Metadata-Version: 2.1
Name: fMRI-Volumetric-Renderer
Version: 0.2.7
Summary: A lightweigt html5 renderer for fmri volumes
Home-page: https://github.com/KappnKrunch/fMRI-Volumetric-Renderer
Author: KappnKrunch
Author-email: personmusicianperson@gmail.com
Classifier: Programming Language :: Python :: 3
Classifier: License :: OSI Approved :: MIT License
Classifier: Operating System :: OS Independent
Requires-Python: >=3.6
License-File: LICENSE
